{"address":{"type":"PostalAddress","addressCountry":"PAK","addressLocality":"Islamabad","addressRegion":"Île-de-France","postalCode":"F-75002","streetAddress":"F11"},"revocationList":{"revokedAssertions":[]},"verfication":{"type":"Hosted","allowedOrigins":[],"startsWith":[]},"type":"Issuer","name":"sadsaadsadsadsadasdsd","email":"roots@gmail.com","phone":3330003322,"_id":"5dde43af13bc0c5252a44232","students":[],"courses":[],"did":"did:ethr:0xce917d74c5bc1d7d036a70aed689b000e6fd86c2","createdAt":"2019-11-27T09:36:47.555Z","updatedAt":"2019-11-27T09:36:47.555Z","__v":0}