{"address":{"type":"PostalAddress","addressCountry":"France","addressLocality":"Paris","addressRegion":"Île-de-France","postalCode":"F-75002","streetAddress":"38 avenue de lOpera"},"revocationList":{"revokedAssertions":[]},"verfication":{"type":"Hosted","allowedOrigins":[],"startsWith":[]},"type":"Issuer","name":"ho la la","email":"asdasd","phone":0,"_id":"5dc92e4c0ce4e73b297c0bba","favoriteSchools":[],"students":[],"courses":[],"did":"did:ethr:0xd2ec735ce502cfe3c817a0cff539aca476d0c0c0","createdAt":"2019-11-11T09:47:56.025Z","updatedAt":"2019-11-11T09:47:56.025Z","__v":0}